.bumpversion.cfg
.flake8
.gitignore
.isort.cfg
.pre-commit-config.yaml
.readthedocs.yml
AUTHORS.rst
CHANGELOG.rst
CONTRIBUTING.rst
INSTALLATION.rst
LICENSE
README.rst
VERSION
build_cffi.py
bump
changethelog.py
environment_dev.yml
pyproject.toml
setup.cfg
setup.py
.github/workflows/merge-me.yaml
.github/workflows/merge-to-dev.yaml
.github/workflows/publish-to-pypi.yaml
.github/workflows/run-tutorials.yaml
.github/workflows/tag-release.yaml
.github/workflows/test_build_macos.yaml
.github/workflows/test_suite.yaml
ci/macos-latest-env.yml
ci/ubuntu-latest-env.yml
devel/TestFindHalos.py
devel/estimated_mem_usage_plot.py
devel/filter_valgrind.py
devel/peak_memory_usage.png
devel/prepare_gh_logs_for_diff.py
devel/prepare_log_for_diff.py
devel/simulate_mcmc_memory_leak.py
devel/simulate_mcmc_memory_leak_lightcone.py
devel/valgrind-python.supp
devel/valgrind-suppress-all-but-c.supp
devel/visualise_boxes_and_power.ipynb
docs/Makefile
docs/authors.rst
docs/changelog.rst
docs/conf.py
docs/contributing.rst
docs/design.rst
docs/environment.yaml
docs/index.rst
docs/installation.rst
docs/notes_for_developers.rst
docs/readme.rst
docs/spelling_wordlist.txt
docs/tutorials.rst
docs/faqs/installation_faq.rst
docs/faqs/misc.rst
docs/reference/index.rst
docs/reference/py21cmfast.rst
docs/templates/class.rst
docs/templates/module.rst
docs/tutorials/coeval_cubes.ipynb
docs/tutorials/gather_data.ipynb
docs/tutorials/lightcones.ipynb
docs/tutorials/mini-halos.ipynb
docs/tutorials/relative_velocities.ipynb
examples/runconfig_example.yml
joss-paper/.gitignore
joss-paper/Makefile
joss-paper/apa.csl
joss-paper/joss-logo.png
joss-paper/latex.template
joss-paper/lightcone.pdf
joss-paper/make-example-plots.py
joss-paper/paper.bib
joss-paper/paper.md
joss-paper/xH_history.pdf
joss-paper/yuxiangs-plot-small.png
src/21cmFAST.egg-info/PKG-INFO
src/21cmFAST.egg-info/SOURCES.txt
src/21cmFAST.egg-info/dependency_links.txt
src/21cmFAST.egg-info/entry_points.txt
src/21cmFAST.egg-info/not-zip-safe
src/21cmFAST.egg-info/requires.txt
src/21cmFAST.egg-info/top_level.txt
src/py21cmfast/__init__.py
src/py21cmfast/_cfg.py
src/py21cmfast/_logging.py
src/py21cmfast/_utils.py
src/py21cmfast/_version.py
src/py21cmfast/cache_tools.py
src/py21cmfast/cli.py
