Metadata-Version: 2.1
Name: 21cmFAST
Version: 3.4.0
Summary: A semi-numerical cosmological simulation code for the 21cm signal
Home-page: https://github.com/21cmFAST/21cmFAST
Author: The 21cmFAST coredev team
Author-email: 21cmfast.coredev@gmail.com
License: MIT license
Keywords: Epoch of Reionization,Cosmology
Classifier: Development Status :: 5 - Production/Stable
Classifier: Intended Audience :: Developers
Classifier: License :: OSI Approved :: MIT License
Classifier: Operating System :: Unix
Classifier: Operating System :: POSIX
Classifier: Programming Language :: Python
Classifier: Programming Language :: Python :: 3
Classifier: Programming Language :: Python :: 3.9
Classifier: Programming Language :: Python :: 3.10
Classifier: Programming Language :: Python :: 3.11
Classifier: Programming Language :: Python :: Implementation :: CPython
License-File: LICENSE
License-File: AUTHORS.rst
Requires-Dist: click
Requires-Dist: numpy<2
Requires-Dist: pyyaml
Requires-Dist: cffi>=1.0
Requires-Dist: scipy
Requires-Dist: astropy>=2.0
Requires-Dist: h5py>=2.8.0
Requires-Dist: cached_property
Requires-Dist: matplotlib
Requires-Dist: bidict
Requires-Dist: cosmotile>=0.2.0
Requires-Dist: attrs
Provides-Extra: tests
Requires-Dist: pre-commit; extra == "tests"
Requires-Dist: pytest>=5.0; extra == "tests"
Requires-Dist: pytest-cov; extra == "tests"
Requires-Dist: tox; extra == "tests"
Requires-Dist: pytest-remotedata>=0.3.2; extra == "tests"
Requires-Dist: powerbox; extra == "tests"
Requires-Dist: pytest-plt; extra == "tests"
Requires-Dist: questionary; extra == "tests"
Provides-Extra: docs
Requires-Dist: nbsphinx; extra == "docs"
Requires-Dist: numpydoc; extra == "docs"
Requires-Dist: sphinx>=1.3; extra == "docs"
Requires-Dist: sphinx-rtd-theme; extra == "docs"
Provides-Extra: dev
Requires-Dist: pre-commit; extra == "dev"
Requires-Dist: pytest>=5.0; extra == "dev"
Requires-Dist: pytest-cov; extra == "dev"
Requires-Dist: tox; extra == "dev"
Requires-Dist: pytest-remotedata>=0.3.2; extra == "dev"
Requires-Dist: powerbox; extra == "dev"
Requires-Dist: pytest-plt; extra == "dev"
Requires-Dist: questionary; extra == "dev"
Requires-Dist: nbsphinx; extra == "dev"
Requires-Dist: numpydoc; extra == "dev"
Requires-Dist: sphinx>=1.3; extra == "dev"
Requires-Dist: sphinx-rtd-theme; extra == "dev"
